python_eda/__init__.py
python_eda/main.py
python_eda-0.1.2.dist-info/entry_points.txt
python_eda-0.1.2.dist-info/WHEEL
python_eda-0.1.2.dist-info/METADATA
python_eda-0.1.2.dist-info/RECORD
