Metadata-Version: 2.1
Name: python-eda
Version: 0.1.2
Summary: A CLI wrapper for sweetviz Python exploratory data analysis (EDA) tool.
Home-page: https://github.com/ThuwarakeshM/python-eda
License: MIT
Keywords: python,data-analytics,data-science,analytics,eda
Author: Thuwarakesh
Author-email: thuwarakesh@gmail.com
Requires-Python: >=3.8,<4.0
Classifier: License :: OSI Approved :: MIT License
Classifier: Programming Language :: Python :: 3
Classifier: Programming Language :: Python :: 3.6
Classifier: Programming Language :: Python :: 3.7
Classifier: Programming Language :: Python :: 3.8
Classifier: Programming Language :: Python :: 3.9
Classifier: Programming Language :: Python :: Implementation
Classifier: Programming Language :: Unix Shell
Classifier: Topic :: Scientific/Engineering :: Information Analysis
Requires-Dist: pandas (>=1.3.2,<2.0.0)
Requires-Dist: sweetviz (>=2.1.3,<3.0.0)
Requires-Dist: typer[all] (>=0.4.0,<0.5.0)
Project-URL: Repository, https://github.com/ThuwarakeshM/python-eda
